none_dict/__init__.py
none_dict-0.0.1.dist-info/METADATA
none_dict-0.0.1.dist-info/WHEEL
none_dict-0.0.1.dist-info/top_level.txt
none_dict-0.0.1.dist-info/RECORD
