Metadata-Version: 2.1
Name: none-dict
Version: 0.0.1
Summary: A dict not raise key error
Home-page: https://github.com/catchzeng/py_pkg
Author: ahua chen
Author-email: cjhdwyyx@163.com
Classifier: Programming Language :: Python :: 3
Classifier: License :: OSI Approved :: MIT License
Classifier: Operating System :: OS Independent
Requires-Python: >=3.6
